password_generator/__init__.py
password_generator/generator.py
secure_pass_gen-0.1.3.dist-info/LICENSE
secure_pass_gen-0.1.3.dist-info/METADATA
secure_pass_gen-0.1.3.dist-info/WHEEL
secure_pass_gen-0.1.3.dist-info/top_level.txt
secure_pass_gen-0.1.3.dist-info/RECORD
